{
  "slug": "$$$",
  "extension": "$$$",
  "name": "Temporary File",
  "summary": "Learn about .$$$ files and view a list of programs that open them.",
  "developer": "N/A",
  "programs": {
    "windows": [
      {
        "name": "Microsoft Notepad",
        "url": "https://fileinfo.com/software/microsoft/notepad"
      },
      {
        "name": "Apple TextEdit",
        "url": "https://fileinfo.com/software/apple/textedit"
      },
      {
        "name": "Open over 400 file formats with File Viewer Plus.Free Download",
        "url": "https://fileinfo.com/software/windows_file_viewer?ref=462&b=1"
      }
    ]
  },
  "technical_info": {
    "content": [
      "Programs that support $$$ files typically generate them automatically and then delete them when the program closes appropriately. However, in some cases, $$$ files remain in the system and require manual removal. If you find a $$$ file, check the software that created it before deleting it to avoid losing important data."
    ]
  },
  "more_information": {
    "description": [
      "A $$$ file is a temporary file created by various programs to store backup data for the original file in case it becomes corrupted, the software crashes, or the user needs to recover unsaved changes. It may contain plain text or binary data specific to the software, depending on the program that created it. $$$ files are not meant to be opened manually but may be helpful for data recovery if an application crashes unexpectedly."
    ]
  },
  "how_to_open": {
    "instructions": [
      "$$$ files are not meant to be opened by a user. Instead, the program that generated it references the file to safeguard against losing the original file.",
      "If you need to open a $$$ file, you may be able to open and view its contents with a text editor, such as Microsoft Notepad (Windows) and Apple TextEdit (macOS), if it stores plain text."
    ]
  },
  "images": [
    {
      "url": "https://fileinfo.com/svg/logo.svg",
      "alt": "FileInfo.com"
    },
    {
      "url": "https://fileinfo.com/svg/random.svg",
      "alt": "random"
    },
    {
      "url": "https://fileinfo.com/svg/search-white.svg",
      "alt": "search"
    },
    {
      "url": "https://fileinfo.com/svg/menu.svg",
      "alt": "open menu"
    },
    {
      "url": "https://fileinfo.com/svg/close.svg",
      "alt": "close menu"
    },
    {
      "url": "https://fileinfo.com/svg/settings.svg",
      "alt": "settings"
    }
  ],
  "sources": [
    {
      "url": "https://fileinfo.com/extension/$$$",
      "source": "fileinfo.com",
      "retrieved_at": "2025-11-01T22:32:42.294Z"
    }
  ],
  "last_updated": "2025-11-01T22:32:42.294Z",
  "category": "other",
  "related": [],
  "containers": []
}