{
  "slug": "asef",
  "extension": "asef",
  "name": "Adobe Swatch Exchange File",
  "summary": "Learn about .ASEF files and view a list of programs that open them.",
  "developer": "Adobe Systems",
  "programs": {
    "windows": [
      {
        "name": "Open over 400 file formats with File Viewer Plus.Free Download",
        "url": "https://fileinfo.com/software/windows_file_viewer?ref=9113&b=1"
      },
      {
        "name": "Adobe Illustrator 2025",
        "url": "https://fileinfo.com/software/adobe/illustrator"
      },
      {
        "name": "Adobe InDesign 2023",
        "url": "https://fileinfo.com/software/adobe/indesign"
      }
    ]
  },
  "more_information": {
    "description": [
      "File used by Adobe InCopy, InDesign and Illustrator, professional page layout and graphic designing applications; similar to the more common .ASE swatch file extension; contains a saved collection of colors; enables sharing between illustrators and publishers in order to use different color swatches."
    ]
  },
  "images": [
    {
      "url": "https://fileinfo.com/svg/logo.svg",
      "alt": "FileInfo.com"
    },
    {
      "url": "https://fileinfo.com/svg/random.svg",
      "alt": "random"
    },
    {
      "url": "https://fileinfo.com/svg/search-white.svg",
      "alt": "search"
    },
    {
      "url": "https://fileinfo.com/svg/menu.svg",
      "alt": "open menu"
    },
    {
      "url": "https://fileinfo.com/svg/close.svg",
      "alt": "close menu"
    },
    {
      "url": "https://fileinfo.com/svg/settings.svg",
      "alt": "settings"
    }
  ],
  "sources": [
    {
      "url": "https://fileinfo.com/extension/asef",
      "source": "fileinfo.com",
      "retrieved_at": "2025-11-01T22:32:42.332Z"
    }
  ],
  "last_updated": "2025-11-01T22:32:42.332Z",
  "category": "other",
  "related": [],
  "containers": []
}