{
  "slug": "awk",
  "extension": "awk",
  "name": ".AWK",
  "summary": "Learn about .AWK files and view a list of programs that open them.",
  "developer": "Free Software Foundation",
  "programs": {
    "windows": [
      {
        "name": "Open over 400 file formats with File Viewer Plus.Free Download",
        "url": "https://fileinfo.com/software/windows_file_viewer?ref=1090&b=1"
      },
      {
        "name": "awk",
        "url": "https://www.gnu.org/software/gawk/manual/gawk.html"
      },
      {
        "name": "MacVim",
        "url": "https://fileinfo.com/software/macvim/macvim"
      },
      {
        "name": "Apple TextEdit",
        "url": "https://fileinfo.com/software/apple/textedit"
      },
      {
        "name": "Vim",
        "url": "https://fileinfo.com/software/vim/vim"
      }
    ]
  },
  "images": [
    {
      "url": "https://fileinfo.com/svg/logo.svg",
      "alt": "FileInfo.com"
    },
    {
      "url": "https://fileinfo.com/svg/random.svg",
      "alt": "random"
    },
    {
      "url": "https://fileinfo.com/svg/search-white.svg",
      "alt": "search"
    },
    {
      "url": "https://fileinfo.com/svg/menu.svg",
      "alt": "open menu"
    },
    {
      "url": "https://fileinfo.com/svg/close.svg",
      "alt": "close menu"
    },
    {
      "url": "https://fileinfo.com/svg/settings.svg",
      "alt": "settings"
    }
  ],
  "sources": [
    {
      "url": "https://fileinfo.com/extension/awk",
      "source": "fileinfo.com",
      "retrieved_at": "2025-11-01T20:11:14.972Z"
    }
  ],
  "last_updated": "2025-11-01T20:11:14.972Z"
}