{
  "slug": "capx",
  "extension": "capx",
  "name": "Construct Compressed Project File",
  "summary": "Learn about .CAPX files and view a list of programs that open them.",
  "developer": "Scirra",
  "programs": {
    "windows": [
      {
        "name": "Open over 400 file formats with File Viewer Plus.Free Download",
        "url": "https://fileinfo.com/software/windows_file_viewer?ref=8149&b=1"
      }
    ]
  },
  "technical_info": {
    "content": [
      "CAPX files also include the .CAPROJ XML project file that is used as the entry point to an uncompressed project.",
      "NOTE: To save a Construct project as a CAPX file, choose File → Save As Single File... from the application menu."
    ]
  },
  "more_information": {
    "description": [
      "Game development project created by Construct, a program used for making 2D games for iOS, Android, HTML5, Chrome, and other platforms; saves all project files in a compressed .ZIP format; includes graphics, sounds, physics models, and game events; used for saving and transporting the entire project as a single archive."
    ]
  },
  "images": [
    {
      "url": "https://fileinfo.com/svg/logo.svg",
      "alt": "FileInfo.com"
    },
    {
      "url": "https://fileinfo.com/svg/random.svg",
      "alt": "random"
    },
    {
      "url": "https://fileinfo.com/svg/search-white.svg",
      "alt": "search"
    },
    {
      "url": "https://fileinfo.com/svg/menu.svg",
      "alt": "open menu"
    },
    {
      "url": "https://fileinfo.com/svg/close.svg",
      "alt": "close menu"
    },
    {
      "url": "https://fileinfo.com/svg/settings.svg",
      "alt": "settings"
    },
    {
      "url": "https://fileinfo.com/img/ss/sm/capx_8572.png",
      "alt": "Screenshot of a .capx file in Capella 8",
      "caption": "CAPX file open in Capella 8"
    }
  ],
  "sources": [
    {
      "url": "https://fileinfo.com/extension/capx",
      "source": "fileinfo.com",
      "retrieved_at": "2025-11-02T02:43:26.634Z"
    }
  ],
  "last_updated": "2025-11-02T02:43:26.634Z"
}