{
  "slug": "chck",
  "extension": "chck",
  "name": "Microsoft Exchange Server Database Check File",
  "summary": "Learn about .CHCK files and view a list of programs that open them.",
  "developer": "Microsoft",
  "category": "database",
  "category_slug": "database",
  "programs": {
    "windows": [
      {
        "name": "Open over 400 file formats with File Viewer Plus.Free Download",
        "url": "https://fileinfo.com/software/windows_file_viewer?ref=12521&b=1"
      },
      {
        "name": "Microsoft Exchange Server",
        "url": "https://fileinfo.com/software/microsoft/exchange_server"
      }
    ]
  },
  "technical_info": {
    "content": [
      "Microsoft Exchange Server is a business server that allows users to send emails and maintain a calendar and contacts list. Administrators can perform health checks of Exchange Server databases. Doing so produces a CHCK file."
    ]
  },
  "more_information": {
    "description": [
      "A CHCK file is created as a result of health monitoring checks on Microsoft Exchange Server. It contains informaiton about the overall status and operationalization of the server’s database. Microsoft Exchange Server is used primarily as emailing server and lets you maintain your business contacts and calendars. Exchange server administrators use its EseUtil to check it’s database health.",
      "A CHCK file is a database check file created by Microsoft Exchange Server. It contains information about a database's health. CHCK files are created using Microsoft Exchange Server's EseUtil."
    ]
  },
  "related": [
    "3d",
    "3d2",
    "3dm",
    "3ds",
    "3ds-to-dae",
    "3ds-to-dwg",
    "3ds-to-fbx",
    "3ds-to-glb",
    "3ds-to-gltf",
    "3ds-to-obj",
    "3ds-to-pdf",
    "3ds-to-ply",
    "3ds-to-stl",
    "3ds-to-usdz",
    "3mf",
    "3mf-to-3ds",
    "3mf-to-dae",
    "3mf-to-glb",
    "3mf-to-html",
    "3mf-to-obj"
  ],
  "images": [
    {
      "url": "https://fileinfo.com/svg/logo.svg",
      "alt": "FileInfo.com"
    },
    {
      "url": "https://fileinfo.com/svg/random.svg",
      "alt": "random"
    },
    {
      "url": "https://fileinfo.com/svg/search-white.svg",
      "alt": "search"
    },
    {
      "url": "https://fileinfo.com/svg/menu.svg",
      "alt": "open menu"
    },
    {
      "url": "https://fileinfo.com/svg/close.svg",
      "alt": "close menu"
    },
    {
      "url": "https://fileinfo.com/svg/settings.svg",
      "alt": "settings"
    }
  ],
  "sources": [
    {
      "url": "https://docs.fileformat.com/database/chck/",
      "source": "fileformat.com",
      "retrieved_at": "2025-11-02T02:43:26.503Z"
    },
    {
      "url": "https://fileinfo.com/extension/chck",
      "source": "fileinfo.com",
      "retrieved_at": "2025-11-02T02:43:26.503Z"
    }
  ],
  "last_updated": "2025-11-02T02:43:26.503Z"
}