{
  "slug": "htc",
  "extension": "htc",
  "name": "HTML Component File",
  "summary": "Learn about .HTC files and view a list of programs that open them.",
  "developer": "Microsoft",
  "category": "web",
  "category_slug": "web",
  "programs": {
    "windows": [
      {
        "name": "Microsoft Web Platform Extensions",
        "url": "https://file.org/free-download/microsoft-web-platform-extensions"
      },
      {
        "name": "progeCAD Professional",
        "url": "https://file.org/free-download/progecad"
      },
      {
        "name": "Untis",
        "url": "https://file.org/free-download/untis"
      },
      {
        "name": "Macromedia Dreamweaver MX",
        "url": "https://file.org/free-download/macromedia-dreamweaver-mx"
      },
      {
        "name": "AViCAD Professional",
        "url": "https://file.org/free-download/avicad-professional"
      },
      {
        "name": "MasterClips MediaPaq Browser",
        "url": "https://file.org/free-download/masterclips-mediapaq-browser"
      },
      {
        "name": "OAGTP",
        "url": "https://file.org/free-download/oagtp"
      },
      {
        "name": "Open over 400 file formats with File Viewer Plus.Free Download",
        "url": "https://fileinfo.com/software/windows_file_viewer?ref=3984&b=1"
      },
      {
        "name": "Microsoft Internet Explorer",
        "url": "https://fileinfo.com/software/microsoft/internet_explorer"
      },
      {
        "name": "MacroMates TextMate",
        "url": "https://fileinfo.com/software/macromates/textmate"
      }
    ]
  },
  "technical_info": {
    "content": [
      "HTC files are non-standard and are not compatible with all browser types."
    ]
  },
  "more_information": {
    "description": [
      "An HTC file is a web file format file used by Microsoft Internet Explorer. It contains definitions for HTML components that perform small functions for performing different tasks inside the web browser. Functionality defined inside HTC files is reusable and is accessible across multiple HTML pages.",
      "File used by Internet Explorer, a common Web browser that displays the content of Web pages; contains definitions for HTML Components that define dynamic behavior within Web pages; designed to contain functions that are reusable across multiple .HTML pages; stored in plain text format."
    ]
  },
  "related": [
    "3d",
    "3d2",
    "3dm",
    "3ds",
    "3ds-to-dae",
    "3ds-to-dwg",
    "3ds-to-fbx",
    "3ds-to-glb",
    "3ds-to-gltf",
    "3ds-to-obj",
    "3ds-to-pdf",
    "3ds-to-ply",
    "3ds-to-stl",
    "3ds-to-usdz",
    "3mf",
    "3mf-to-3ds",
    "3mf-to-dae",
    "3mf-to-glb",
    "3mf-to-html",
    "3mf-to-obj"
  ],
  "images": [
    {
      "url": "https://assets.file.org/images/fileorg-logo-440x90-4-8b.png",
      "alt": "File.org logo"
    },
    {
      "url": "https://fileinfo.com/svg/logo.svg",
      "alt": "FileInfo.com"
    },
    {
      "url": "https://fileinfo.com/svg/random.svg",
      "alt": "random"
    },
    {
      "url": "https://fileinfo.com/svg/search-white.svg",
      "alt": "search"
    },
    {
      "url": "https://fileinfo.com/svg/menu.svg",
      "alt": "open menu"
    },
    {
      "url": "https://fileinfo.com/svg/close.svg",
      "alt": "close menu"
    },
    {
      "url": "https://fileinfo.com/svg/settings.svg",
      "alt": "settings"
    }
  ],
  "sources": [
    {
      "url": "https://file.org",
      "source": "file.org",
      "retrieved_at": "2025-11-02T02:43:26.397Z"
    },
    {
      "url": "https://docs.fileformat.com/web/htc/",
      "source": "fileformat.com",
      "retrieved_at": "2025-11-02T02:43:26.397Z"
    },
    {
      "url": "https://fileinfo.com/extension/htc",
      "source": "fileinfo.com",
      "retrieved_at": "2025-11-02T02:43:26.397Z"
    }
  ],
  "last_updated": "2025-11-02T02:43:26.397Z"
}