{
  "slug": "ikf",
  "extension": "ikf",
  "name": "INTUS Keyboard File",
  "summary": "Learn about .IKF files and view a list of programs that open them.",
  "developer": "PCS Systemtechnik",
  "programs": {
    "windows": [
      {
        "name": "Open over 400 file formats with File Viewer Plus.Free Download",
        "url": "https://fileinfo.com/software/windows_file_viewer?ref=8474&b=1"
      }
    ]
  },
  "technical_info": {
    "content": [
      "INTUS terminals are used for timecard management (i.e., employees clocking in and out), security access control, diagnostics, and data collection.",
      "NOTE: Only newer INTUS terminal models (i.e., INTUS 5500 and 5600) can use IKF files and the RemoteConf software for updates. Older INTUS terminals, including the INTUS 3100, 3450, and 5300, are managed with INTUS RemoteSetup, the predecessor to RemoteConf."
    ]
  },
  "more_information": {
    "description": [
      "File used by INTUS RemoteConf, a program used for configuring INTUS terminals; contains a mapping between touchscreen events and the underlying functions that are invoked when the events are activated."
    ]
  },
  "images": [
    {
      "url": "https://fileinfo.com/svg/logo.svg",
      "alt": "FileInfo.com"
    },
    {
      "url": "https://fileinfo.com/svg/random.svg",
      "alt": "random"
    },
    {
      "url": "https://fileinfo.com/svg/search-white.svg",
      "alt": "search"
    },
    {
      "url": "https://fileinfo.com/svg/menu.svg",
      "alt": "open menu"
    },
    {
      "url": "https://fileinfo.com/svg/close.svg",
      "alt": "close menu"
    },
    {
      "url": "https://fileinfo.com/svg/settings.svg",
      "alt": "settings"
    }
  ],
  "sources": [
    {
      "url": "https://fileinfo.com/extension/ikf",
      "source": "fileinfo.com",
      "retrieved_at": "2025-11-01T22:32:42.543Z"
    }
  ],
  "last_updated": "2025-11-01T22:32:42.543Z",
  "category": "other",
  "related": [],
  "containers": []
}