{
  "slug": "sin",
  "extension": "sin",
  "name": "Sony Xperia Firmware File",
  "summary": "Learn about .SIN files and view a list of programs that open them.",
  "developer": "Sony",
  "programs": {
    "windows": [
      {
        "name": "Open over 400 file formats with File Viewer Plus.Free Download",
        "url": "https://fileinfo.com/software/windows_file_viewer?ref=10947&b=1"
      }
    ]
  },
  "technical_info": {
    "content": [
      "Most users will not encounter SIN files since they are distributed in FTF files. However, some users may extract them from FTF files in order to modify and create custom firmware files for Xperia devices. Users can unpack SIN files (version 3, 4, and 5) with the UnSin tool."
    ]
  },
  "more_information": {
    "description": [
      "A SIN file is a firmware file used to distribute updates to Sony Xperia smartphones and tablets. It contains data, such as a partition image or kernel image, used to update the Xperia device. SIN files are typically stored in .FTF files, which are flashed on to a device."
    ]
  },
  "images": [
    {
      "url": "https://fileinfo.com/svg/logo.svg",
      "alt": "FileInfo.com"
    },
    {
      "url": "https://fileinfo.com/svg/random.svg",
      "alt": "random"
    },
    {
      "url": "https://fileinfo.com/svg/search-white.svg",
      "alt": "search"
    },
    {
      "url": "https://fileinfo.com/svg/menu.svg",
      "alt": "open menu"
    },
    {
      "url": "https://fileinfo.com/svg/close.svg",
      "alt": "close menu"
    },
    {
      "url": "https://fileinfo.com/svg/settings.svg",
      "alt": "settings"
    }
  ],
  "sources": [
    {
      "url": "https://fileinfo.com/extension/sin",
      "source": "fileinfo.com",
      "retrieved_at": "2025-11-02T02:43:27.102Z"
    }
  ],
  "last_updated": "2025-11-02T02:43:27.102Z"
}