{
  "slug": "ede",
  "extension": "ede",
  "name": "Ensoniq EPS Disk Image",
  "summary": "Learn about .EDE files and view a list of programs that open them.",
  "developer": "Ensoniq",
  "category": "other",
  "containers": [],
  "related": [],
  "technical_info": {
    "content": [
      "Ensoniq released the EPS in 1988 and continued manufacturing it until 1991. The keyboard featured a floppy drive where users could insert floppy disks to add sounds, presets, and songs to the sampler.",
      "While the sampler is no longer in production, music enthusiasts looking to access the sounds stored on floppy disks dump the data and save them in the EDE format. They then play the EDE files or convert them to other file types with software."
    ]
  },
  "how_to_open": {
    "instructions": [
      "You can open EDE files with Chicken Systems Ensoniq Disk Tools in Windows."
    ]
  },
  "how_to_convert": {
    "instructions": [
      "Ensoniq Disk Tools can convert EDE files to several file types, including the following formats:",
      ".MIDI - MIDI Music Data",
      ".SMF - Standard MIDI File",
      ".WAV - WAVE Audio File",
      ".AIFF - Audio Interchange File Format"
    ]
  },
  "programs": {
    "windows": [
      {
        "name": "Open over 400 file formats with File Viewer Plus.Free Download",
        "url": "https://fileinfo.com/software/windows_file_viewer?ref=1728&b=1"
      }
    ]
  },
  "images": [
    {
      "url": "https://fileinfo.com/svg/logo.svg",
      "alt": "FileInfo.com"
    },
    {
      "url": "https://fileinfo.com/svg/random.svg",
      "alt": "random"
    },
    {
      "url": "https://fileinfo.com/svg/search-white.svg",
      "alt": "search"
    },
    {
      "url": "https://fileinfo.com/svg/menu.svg",
      "alt": "open menu"
    },
    {
      "url": "https://fileinfo.com/svg/close.svg",
      "alt": "close menu"
    },
    {
      "url": "https://fileinfo.com/svg/settings.svg",
      "alt": "settings"
    }
  ],
  "sources": [
    {
      "source": "fileinfo.com",
      "url": "https://fileinfo.com/extension/ede",
      "retrieved_at": "2025-11-01T22:32:42.440Z"
    }
  ],
  "last_updated": "2025-11-01T22:32:42.440Z"
}