{
  "slug": "pes",
  "extension": "pes",
  "name": ".PES File Extension",
  "summary": "Learn about .PES files and view a list of programs that open them.",
  "programs": {
    "windows": [
      {
        "name": "Google Chrome",
        "url": "https://fileinfo.com/software/google/chrome"
      },
      {
        "name": "File Viewer Plus",
        "url": "https://fileinfo.com/software/windows_file_viewer?ref=1096"
      },
      {
        "name": "Google Chrome with Embroidery Viewer and Converter plugin",
        "url": "https://fileinfo.com/software/google/chrome"
      }
    ]
  },
  "images": [
    {
      "url": "https://fileinfo.com/svg/logo.svg",
      "alt": "FileInfo.com"
    },
    {
      "url": "https://fileinfo.com/svg/random.svg",
      "alt": "random"
    },
    {
      "url": "https://fileinfo.com/svg/search-white.svg",
      "alt": "search"
    },
    {
      "url": "https://fileinfo.com/svg/menu.svg",
      "alt": "open menu"
    },
    {
      "url": "https://fileinfo.com/svg/close.svg",
      "alt": "close menu"
    },
    {
      "url": "https://fileinfo.com/svg/settings.svg",
      "alt": "settings"
    },
    {
      "url": "https://fileinfo.com/img/ss/sm/pes_1096.png",
      "alt": "Screenshot of a .pes file in Buzz Tools BuzzXplore 4",
      "caption": "PES file open in Buzz Tools BuzzXplore 4"
    },
    {
      "url": "https://fileinfo.com/img/ss/sm/pes_7191.png",
      "alt": "Screenshot of a .pes file in CodeAndWeb PhysicsEditor",
      "caption": "PES file open in CodeAndWeb PhysicsEditor"
    }
  ],
  "sources": [
    {
      "url": "https://fileinfo.com/extension/pes",
      "source": "fileinfo.com",
      "retrieved_at": "2025-11-01T18:24:49.820Z"
    }
  ],
  "last_updated": "2025-11-01T18:24:49.820Z",
  "category": "other",
  "related": [],
  "containers": []
}