{
  "slug": "exopc",
  "extension": "exopc",
  "name": "ExoPC Application",
  "summary": "Learn about .EXOPC files and view a list of programs that open them.",
  "developer": "ExoPC",
  "technical_info": {
    "content": [
      "EXOPC files may contain images, audio, video, and other data files. They include an XML configuration file that describes how to manage the application files when executing the application.",
      "EXOPC files are based on the .MIO format and require the MioEngine platform to execute. They also use the ExoPC UI Layer, which extends MioEngine with ExoPC-specific application features. The files can be tested using the free EXOfactory developer tool.",
      "NOTE: ExoPC applications, also called \"apps,\" are available through the ExoPC app store. They must be certified by ExoPC before being published. The ExoPC company name was renamed EXO U. ExoPC Slate is no longer developed or available for purchase."
    ]
  },
  "programs": {
    "windows": [
      {
        "name": "Open over 400 file formats with File Viewer Plus.Free Download",
        "url": "https://fileinfo.com/software/windows_file_viewer?ref=4718&b=1"
      }
    ]
  },
  "images": [
    {
      "url": "https://fileinfo.com/svg/logo.svg",
      "alt": "FileInfo.com"
    },
    {
      "url": "https://fileinfo.com/svg/random.svg",
      "alt": "random"
    },
    {
      "url": "https://fileinfo.com/svg/search-white.svg",
      "alt": "search"
    },
    {
      "url": "https://fileinfo.com/svg/menu.svg",
      "alt": "open menu"
    },
    {
      "url": "https://fileinfo.com/svg/close.svg",
      "alt": "close menu"
    },
    {
      "url": "https://fileinfo.com/svg/settings.svg",
      "alt": "settings"
    }
  ],
  "sources": [
    {
      "source": "fileinfo.com",
      "url": "https://fileinfo.com/extension/exopc",
      "retrieved_at": "2025-11-02T02:43:26.730Z"
    }
  ],
  "last_updated": "2025-11-02T02:43:26.730Z"
}