{
  "slug": "jas",
  "extension": "jas",
  "name": "Cheetah3D Model File",
  "summary": "Learn about .JAS files and view a list of programs that open them.",
  "developer": "Cheetah3D",
  "category": "other",
  "containers": [],
  "related": [],
  "technical_info": {
    "content": [
      "Unity can import and modify JAS files, as well as convert JAS files to the Autodesk .FBX format."
    ]
  },
  "programs": {
    "windows": [
      {
        "name": "Open over 400 file formats with File Viewer Plus.Free Download",
        "url": "https://fileinfo.com/software/windows_file_viewer?ref=5880&b=1"
      },
      {
        "name": "Unity Technologies Unity",
        "url": "https://fileinfo.com/software/unity_technologies/unity"
      },
      {
        "name": "PaintShop Pro",
        "url": "https://fileinfo.com/software/corel/paintshop_pro"
      }
    ]
  },
  "images": [
    {
      "url": "https://fileinfo.com/svg/logo.svg",
      "alt": "FileInfo.com"
    },
    {
      "url": "https://fileinfo.com/svg/random.svg",
      "alt": "random"
    },
    {
      "url": "https://fileinfo.com/svg/search-white.svg",
      "alt": "search"
    },
    {
      "url": "https://fileinfo.com/svg/menu.svg",
      "alt": "open menu"
    },
    {
      "url": "https://fileinfo.com/svg/close.svg",
      "alt": "close menu"
    },
    {
      "url": "https://fileinfo.com/svg/settings.svg",
      "alt": "settings"
    }
  ],
  "sources": [
    {
      "source": "fileinfo.com",
      "url": "https://fileinfo.com/extension/jas",
      "retrieved_at": "2025-11-01T22:32:42.559Z"
    }
  ],
  "last_updated": "2025-11-01T22:32:42.559Z"
}