{
  "slug": "lcd",
  "extension": "lcd",
  "name": "ABBYY FineReader Language File",
  "summary": "Learn about .LCD files and view a list of programs that open them.",
  "developer": "ABBYY",
  "technical_info": {
    "content": [
      "FineReader is a suite of PDF management tools that allows users to open, edit, and convert PDF documents. However, before a user can edit a PDF's text, FineReader must process the document's text and convert it to an editable format.",
      "To process and convert text, FineReader uses language-specific data stored in a set of LCD files (installed with the program). After FineReader uses its LCD files to process a document's text, a user can edit that text."
    ]
  },
  "how_to_open": {
    "instructions": [
      "LCD files are not meant to be opened. FineReader automatically loads and uses the data LCD files contain as needed."
    ]
  },
  "programs": {
    "windows": [
      {
        "name": "Open over 400 file formats with File Viewer Plus.Free Download",
        "url": "https://fileinfo.com/software/windows_file_viewer?ref=2321&b=1"
      },
      {
        "name": "EZB Systems UltraISO",
        "url": "https://fileinfo.com/software/ezb_systems/ultraiso"
      },
      {
        "name": "PowerISO",
        "url": "https://fileinfo.com/software/poweriso/poweriso"
      },
      {
        "name": "ESTsoft AlZip",
        "url": "https://fileinfo.com/software/estsoft/alzip"
      }
    ]
  },
  "images": [
    {
      "url": "https://fileinfo.com/svg/logo.svg",
      "alt": "FileInfo.com"
    },
    {
      "url": "https://fileinfo.com/svg/random.svg",
      "alt": "random"
    },
    {
      "url": "https://fileinfo.com/svg/search-white.svg",
      "alt": "search"
    },
    {
      "url": "https://fileinfo.com/svg/menu.svg",
      "alt": "open menu"
    },
    {
      "url": "https://fileinfo.com/svg/close.svg",
      "alt": "close menu"
    },
    {
      "url": "https://fileinfo.com/svg/settings.svg",
      "alt": "settings"
    }
  ],
  "sources": [
    {
      "source": "fileinfo.com",
      "url": "https://fileinfo.com/extension/lcd",
      "retrieved_at": "2025-11-02T02:43:26.867Z"
    }
  ],
  "last_updated": "2025-11-02T02:43:26.867Z"
}