{
  "slug": "voc",
  "extension": "voc",
  "name": "Creative Labs Audio File",
  "summary": "Learn about .VOC files and view a list of programs that open them.",
  "developer": "Creative Labs",
  "category": "audio",
  "category_slug": "audio",
  "related": [
    "3d",
    "3d2",
    "3dm",
    "3ds",
    "3ds-to-dae",
    "3ds-to-dwg",
    "3ds-to-fbx",
    "3ds-to-glb",
    "3ds-to-gltf",
    "3ds-to-obj",
    "3ds-to-pdf",
    "3ds-to-ply",
    "3ds-to-stl",
    "3ds-to-usdz",
    "3mf",
    "3mf-to-3ds",
    "3mf-to-dae",
    "3mf-to-glb",
    "3mf-to-html",
    "3mf-to-obj"
  ],
  "technical_info": {
    "content": [
      "In these files, audio information is contained in a 26-byte header. Moreover, a series of subsequent data blocks are also included in it. Data blocks follow the header and every block starts along with a type byte that describes the content. The size of these files is 3 bytes. There are some uncompressed audio formats of these files, for example, WAV or AU, etc. These files can store various sounds of instruments, music files, and digital audio clips."
    ]
  },
  "programs": {
    "windows": [
      {
        "name": "File Viewer Plus",
        "url": "https://fileinfo.com/software/windows_file_viewer?ref=297"
      },
      {
        "name": "Adobe Audition 2023",
        "url": "https://fileinfo.com/software/adobe/audition"
      },
      {
        "name": "Nullsoft Winamp",
        "url": "https://fileinfo.com/software/nullsoft/winamp"
      },
      {
        "name": "VideoLAN VLC media player",
        "url": "https://fileinfo.com/software/videolan/vlc_media_player"
      },
      {
        "name": "AGiliTy",
        "url": "https://fileinfo.com/software/robert_masenten/agility"
      }
    ]
  },
  "images": [
    {
      "url": "https://fileinfo.com/svg/logo.svg",
      "alt": "FileInfo.com"
    },
    {
      "url": "https://fileinfo.com/svg/random.svg",
      "alt": "random"
    },
    {
      "url": "https://fileinfo.com/svg/search-white.svg",
      "alt": "search"
    },
    {
      "url": "https://fileinfo.com/svg/menu.svg",
      "alt": "open menu"
    },
    {
      "url": "https://fileinfo.com/svg/close.svg",
      "alt": "close menu"
    },
    {
      "url": "https://fileinfo.com/svg/settings.svg",
      "alt": "settings"
    },
    {
      "url": "https://fileinfo.com/img/ss/sm/voc_10689.png",
      "alt": "Screenshot of a .voc file in RCA Digital Voice Manager",
      "caption": "VOC file open in RCA Digital Voice Manager"
    }
  ],
  "sources": [
    {
      "source": "fileformat.com",
      "url": "https://docs.fileformat.com/audio/voc/",
      "retrieved_at": "2025-11-02T02:43:26.538Z"
    },
    {
      "source": "fileinfo.com",
      "url": "https://fileinfo.com/extension/voc",
      "retrieved_at": "2025-11-02T02:43:26.538Z"
    }
  ],
  "last_updated": "2025-11-02T02:43:26.538Z"
}