{
  "source": "fileinfo.com",
  "url": "https://fileinfo.com/extension/bdt2",
  "slug": "bdt2",
  "extension": "bdt2",
  "name": ".BDT2 File Extension",
  "type_name": "BEEDOCS Timeline 3D 2 Document",
  "summary": "Learn about .BDT2 files and view a list of programs that open them.",
  "developer": "BEEDOCS",
  "more_information": {
    "description": [
      "Document created by BEEDOCS Timeline 3D 2, a program used for capturing timelines and historical events; may include pictures, dates, sounds, video, notes, and other event information; used for sharing timelines through videos or interactive presentations."
    ]
  },
  "technical_info": {
    "content": [
      "Timeline 3D projects can be published as interactive timelines to the Web, as video to YouTube or iTunes, or as part of a Keynote presentation.",
      "NOTE: Timeline 3D version 3 uses the .BDT3 extension."
    ]
  },
  "programs": {
    "windows": [
      {
        "name": "Open over 400 file formats with File Viewer Plus.Free Download",
        "url": "https://fileinfo.com/software/windows_file_viewer?ref=7530&b=1"
      }
    ]
  },
  "images": [
    {
      "url": "https://fileinfo.com/svg/logo.svg",
      "alt": "FileInfo.com"
    },
    {
      "url": "https://fileinfo.com/svg/random.svg",
      "alt": "random"
    },
    {
      "url": "https://fileinfo.com/svg/search-white.svg",
      "alt": "search"
    },
    {
      "url": "https://fileinfo.com/svg/menu.svg",
      "alt": "open menu"
    },
    {
      "url": "https://fileinfo.com/svg/close.svg",
      "alt": "close menu"
    },
    {
      "url": "https://fileinfo.com/svg/settings.svg",
      "alt": "settings"
    }
  ]
}