{
  "source": "fileinfo.com",
  "url": "https://fileinfo.com/extension/fppx",
  "slug": "fppx",
  "extension": "fppx",
  "name": ".FPPX File Extension",
  "type_name": "Microsoft Fresh Paint Painting File",
  "summary": "Learn about .FPPX files and view a list of programs that open them.",
  "developer": "Microsoft",
  "more_information": {
    "description": [
      "Native image format of Fresh Paint, a Microsoft app used to created digital oil paint artwork; stores a painting made up of paint brush, pencil, and pen strokes."
    ]
  },
  "technical_info": {
    "content": [
      "Fresh Paint allows you to save your paintings in the FPPX format, as well as the JPEG and PNG formats. Fresh Paint also allows you to import the FPPX format.",
      "The location of FPPX files depends on where the user chose to save it. However, the default location for saving FPPX files is the following directory:",
      "C:\\​Users\\​<username>\\​AppData\\​Local\\​Packages\\​Microsoft.FreshPaint_8wekyb3d8bbwe\\​ LocalState\\​Artworks"
    ]
  },
  "programs": {
    "windows": [
      {
        "name": "Open over 400 file formats with File Viewer Plus.Free Download",
        "url": "https://fileinfo.com/software/windows_file_viewer?ref=10102&b=1"
      }
    ]
  },
  "images": [
    {
      "url": "https://fileinfo.com/svg/logo.svg",
      "alt": "FileInfo.com"
    },
    {
      "url": "https://fileinfo.com/svg/random.svg",
      "alt": "random"
    },
    {
      "url": "https://fileinfo.com/svg/search-white.svg",
      "alt": "search"
    },
    {
      "url": "https://fileinfo.com/svg/menu.svg",
      "alt": "open menu"
    },
    {
      "url": "https://fileinfo.com/svg/close.svg",
      "alt": "close menu"
    },
    {
      "url": "https://fileinfo.com/svg/settings.svg",
      "alt": "settings"
    }
  ]
}