{
  "source": "fileinfo.com",
  "url": "https://fileinfo.com/extension/jxr",
  "slug": "jxr",
  "extension": "jxr",
  "name": ".JXR File Extension",
  "type_name": "JPEG XR Image",
  "summary": "Learn about .JXR files and view a list of programs that open them.",
  "developer": "Microsoft",
  "more_information": {
    "description": [
      "A JXR file is an image saved in the JPEG XR image format. It likely contains a high-definition, continuous-tone digital photo. The JPEG XR format is an improved version of the JPEG format. Thus, JXR files are similar to, but usually higher quality than, .JPG files."
    ]
  },
  "technical_info": {
    "content": [
      "In 2007, Microsoft and the Joint Photographic Experts Group (JPEG) partnered to turn Microsoft's HD Photo (also known as Windows Media Photo) image format into an extension of the JPEG standard. The resulting format was named JPEG extended range, or JPEG XR.",
      "The JPEG XR format improves on the standard JPEG format in several ways. Most notably, JXR images can include more accurate colors than JPEGs, making the JXR format better suited for storing high-resolution digital photos. JPEG XR also supports:",
      "Higher compression rations than normal JPEG (producing smaller-sized files)",
      "Both lossless and lossy compression",
      "An alpha channel used to provide transparency"
    ]
  },
  "how_to_open": {
    "instructions": [
      "You can open a JXR file with Microsoft Photos, XnViewMP, or ImageMagick. Additionally, several image viewers and editors, such as Adobe Photoshop, GIMP, and IrfanView, can open JXR files after users install an associated plug-in."
    ]
  },
  "how_to_convert": {
    "instructions": [
      "Microsoft Photos, XnViewMP, and ImageMagick can convert JXR files to other image formats. For example, Microsoft Photos can convert JXR files to the following formats:",
      ".JPG, .JPEG, .JPE - JPEG Image",
      ".PNG - Portable Network Graphic",
      ".TIF, .TIFF - Tagged Image File Format",
      ".BMP - Bitmap Image"
    ]
  },
  "programs": {
    "windows": [
      {
        "name": "Microsoft Photos",
        "url": "https://fileinfo.com/software/microsoft/photos"
      },
      {
        "name": "XnViewMP",
        "url": "https://fileinfo.com/software/xnsoft/xnviewmp"
      },
      {
        "name": "ImageMagick",
        "url": "https://fileinfo.com/software/imagemagick/imagemagick"
      },
      {
        "name": "Adobe Photoshop",
        "url": "https://fileinfo.com/software/adobe/photoshop"
      },
      {
        "name": "GIMP",
        "url": "https://fileinfo.com/software/gimp/gimp"
      },
      {
        "name": "IrfanView",
        "url": "https://fileinfo.com/software/irfanview/irfanview"
      },
      {
        "name": "Microsoft Photos",
        "url": "https://fileinfo.com/software/microsoft/photos"
      },
      {
        "name": "XnViewMP",
        "url": "https://fileinfo.com/software/xnsoft/xnviewmp"
      },
      {
        "name": "ImageMagick",
        "url": "https://fileinfo.com/software/imagemagick/imagemagick"
      },
      {
        "name": "Open and view .JXR files with File Viewer Plus.Free Download",
        "url": "https://fileinfo.com/software/windows_file_viewer?ref=4529&b=1"
      },
      {
        "name": "File Viewer Plus",
        "url": "https://fileinfo.com/software/windows_file_viewer?ref=4529"
      },
      {
        "name": "Microsoft Photos",
        "url": "https://fileinfo.com/software/microsoft/photos"
      }
    ]
  },
  "images": [
    {
      "url": "https://fileinfo.com/svg/logo.svg",
      "alt": "FileInfo.com"
    },
    {
      "url": "https://fileinfo.com/svg/random.svg",
      "alt": "random"
    },
    {
      "url": "https://fileinfo.com/svg/search-white.svg",
      "alt": "search"
    },
    {
      "url": "https://fileinfo.com/svg/menu.svg",
      "alt": "open menu"
    },
    {
      "url": "https://fileinfo.com/svg/close.svg",
      "alt": "close menu"
    },
    {
      "url": "https://fileinfo.com/svg/settings.svg",
      "alt": "settings"
    },
    {
      "url": "https://fileinfo.com/img/ss/sm/jxr_4529.jpg",
      "alt": "Screenshot of a .jxr file in Microsoft Photos",
      "caption": "JXR file open in Microsoft Photos"
    }
  ]
}