{
  "source": "fileinfo.com",
  "url": "https://fileinfo.com/extension/nkc",
  "slug": "nkc",
  "extension": "nkc",
  "name": ".NKC File Extension",
  "type_name": "Kontakt Library Data File",
  "summary": "Learn about .NKC files and view a list of programs that open them.",
  "developer": "Native Instruments",
  "more_information": {
    "description": [
      "File used by Kontakt audio sampling software; used along with a corresponding .NKX file, which contains the sample and patch information; uses the same filename prefix as the NKX file but is much smaller in size; used as part of the sample library."
    ]
  },
  "programs": {
    "windows": [
      {
        "name": "Open over 400 file formats with File Viewer Plus.Free Download",
        "url": "https://fileinfo.com/software/windows_file_viewer?ref=7871&b=1"
      },
      {
        "name": "Native Instruments Kontakt",
        "url": "https://fileinfo.com/software/native_instruments/kontakt"
      },
      {
        "name": "Native Instruments Kontakt",
        "url": "https://fileinfo.com/software/native_instruments/kontakt"
      }
    ]
  },
  "images": [
    {
      "url": "https://fileinfo.com/svg/logo.svg",
      "alt": "FileInfo.com"
    },
    {
      "url": "https://fileinfo.com/svg/random.svg",
      "alt": "random"
    },
    {
      "url": "https://fileinfo.com/svg/search-white.svg",
      "alt": "search"
    },
    {
      "url": "https://fileinfo.com/svg/menu.svg",
      "alt": "open menu"
    },
    {
      "url": "https://fileinfo.com/svg/close.svg",
      "alt": "close menu"
    },
    {
      "url": "https://fileinfo.com/svg/settings.svg",
      "alt": "settings"
    }
  ]
}