{
  "source": "fileinfo.com",
  "url": "https://fileinfo.com/extension/sesx",
  "slug": "sesx",
  "extension": "sesx",
  "name": ".SESX File Extension",
  "summary": "Learn about .SESX files and view a list of programs that open them.",
  "developer": "Adobe",
  "how_to_open": {
    "instructions": [
      "You can open SESX files only with Adobe Audition (multiplatform). To open an SESX file in Audition, select File → Open and then navigate to and open your SESX file. Also, if you have Audition installed and associated with the SESX file type, you can simply double-click your SESX file to open it."
    ]
  },
  "how_to_convert": {
    "instructions": [
      "Adobe Audition can convert SESX files to various formats. To convert a SESX file with Audition, select File → Export. Here are some of the possible formats:",
      ".RMI - RMID MIDI",
      ".MID - MIDI",
      ".AVI - Audio Video Interleave",
      ".WMV - Windows Media Video",
      ".ASF - Advanced Systems Format",
      ".MOV - Apple QuickTime Movie",
      ".WAV - WAVE Audio",
      ".AAC - Advanced Audio Coding",
      ".AIFF - Audio Interchange File Format",
      ".OGG - Ogg Vorbis Audio",
      ".APE - Monkey's Audio Lossless Audio",
      ".M4A - MPEG-4 Audio",
      ".WMA - Windows Media Audio",
      ".MP3 - MP3 Audio",
      ".VOX - Dialogic Voice Audio",
      ".SND - Sound File",
      ".SES - Audition Session"
    ]
  },
  "programs": {
    "windows": [
      {
        "name": "Adobe Audition",
        "url": "https://fileinfo.com/software/adobe/audition"
      },
      {
        "name": "Open over 400 file formats with File Viewer Plus.Free Download",
        "url": "https://fileinfo.com/software/windows_file_viewer?ref=6815&b=1"
      },
      {
        "name": "Adobe Audition 2023",
        "url": "https://fileinfo.com/software/adobe/audition"
      },
      {
        "name": "Adobe Audition 2023",
        "url": "https://fileinfo.com/software/adobe/audition"
      }
    ]
  },
  "images": [
    {
      "url": "https://fileinfo.com/svg/logo.svg",
      "alt": "FileInfo.com"
    },
    {
      "url": "https://fileinfo.com/svg/random.svg",
      "alt": "random"
    },
    {
      "url": "https://fileinfo.com/svg/search-white.svg",
      "alt": "search"
    },
    {
      "url": "https://fileinfo.com/svg/menu.svg",
      "alt": "open menu"
    },
    {
      "url": "https://fileinfo.com/svg/close.svg",
      "alt": "close menu"
    },
    {
      "url": "https://fileinfo.com/svg/settings.svg",
      "alt": "settings"
    },
    {
      "url": "https://fileinfo.com/img/ss/sm/sesx_6815.jpg",
      "alt": "Screenshot of a .sesx file in Adobe Audition 2023",
      "caption": "SESX file open in Adobe Audition 2023"
    }
  ]
}