{
  "source": "fileinfo.com",
  "url": "https://fileinfo.com/extension/vso",
  "slug": "vso",
  "extension": "vso",
  "name": ".VSO File Extension",
  "type_name": "Compiled Vertex Shader File",
  "summary": "Learn about .VSO files and view a list of programs that open them.",
  "developer": "N/A",
  "more_information": {
    "description": [
      "File used by the vertex shader tool included in the Microsoft DirectX SDK; compiled version of the .VSH file; contains transformation and lighting operations state information for objects; also contains data variables based on x, y, and z coordinates."
    ]
  },
  "programs": {
    "windows": [
      {
        "name": "Open over 400 file formats with File Viewer Plus.Free Download",
        "url": "https://fileinfo.com/software/windows_file_viewer?ref=8983&b=1"
      }
    ]
  },
  "images": [
    {
      "url": "https://fileinfo.com/svg/logo.svg",
      "alt": "FileInfo.com"
    },
    {
      "url": "https://fileinfo.com/svg/random.svg",
      "alt": "random"
    },
    {
      "url": "https://fileinfo.com/svg/search-white.svg",
      "alt": "search"
    },
    {
      "url": "https://fileinfo.com/svg/menu.svg",
      "alt": "open menu"
    },
    {
      "url": "https://fileinfo.com/svg/close.svg",
      "alt": "close menu"
    },
    {
      "url": "https://fileinfo.com/svg/settings.svg",
      "alt": "settings"
    }
  ]
}