{
  "source": "fileinfo.com",
  "url": "https://fileinfo.com/extension/wk3",
  "slug": "wk3",
  "extension": "wk3",
  "name": ".WK3 File Extension",
  "type_name": "Lotus 3 Worksheet",
  "summary": "Learn about .WK3 files and view a list of programs that open them.",
  "developer": "IBM",
  "more_information": {
    "description": [
      "Spreadsheet file created by Lotus 1-2-3, version 3; stores data in cells, which are organized into a grid of rows and columns; may be used for a variety of data-entry purposes."
    ]
  },
  "technical_info": {
    "content": [
      "You can open WK3 files with IBM Lotus 1-2-3 and Microsoft Excel. However, IBM Lotus 1-2-3 is discontinued and Excel 2007 and later does not support WK3 files."
    ]
  },
  "programs": {
    "windows": [
      {
        "name": "Open over 400 file formats with File Viewer Plus.Free Download",
        "url": "https://fileinfo.com/software/windows_file_viewer?ref=943&b=1"
      }
    ]
  },
  "images": [
    {
      "url": "https://fileinfo.com/svg/logo.svg",
      "alt": "FileInfo.com"
    },
    {
      "url": "https://fileinfo.com/svg/random.svg",
      "alt": "random"
    },
    {
      "url": "https://fileinfo.com/svg/search-white.svg",
      "alt": "search"
    },
    {
      "url": "https://fileinfo.com/svg/menu.svg",
      "alt": "open menu"
    },
    {
      "url": "https://fileinfo.com/svg/close.svg",
      "alt": "close menu"
    },
    {
      "url": "https://fileinfo.com/svg/settings.svg",
      "alt": "settings"
    }
  ]
}