{
  "source": "fileinfo.com",
  "url": "https://fileinfo.com/extension/worksheet",
  "slug": "worksheet",
  "extension": "worksheet",
  "name": ".WORKSHEET File Extension",
  "type_name": "BBEdit Shell Worksheet File",
  "summary": "Learn about .WORKSHEET files and view a list of programs that open them.",
  "developer": "Bare Bones Software",
  "more_information": {
    "description": [
      "Developer file created by BBEdit, a Mac OS X source code development program; stores an interactive programmer worksheet, which can save source code text as well as execute commands in-line while editing; used for adding Unix command line features to source code development."
    ]
  },
  "technical_info": {
    "content": [
      "The BBEdit shell worksheet component is similar to the older Macintosh Programmer's Workbench (MPW)."
    ]
  },
  "programs": {
    "windows": [
      {
        "name": "Open over 400 file formats with File Viewer Plus.Free Download",
        "url": "https://fileinfo.com/software/windows_file_viewer?ref=6157&b=1"
      },
      {
        "name": "Bare Bones BBEdit",
        "url": "https://fileinfo.com/software/bare_bones/bbedit"
      }
    ]
  },
  "images": [
    {
      "url": "https://fileinfo.com/svg/logo.svg",
      "alt": "FileInfo.com"
    },
    {
      "url": "https://fileinfo.com/svg/random.svg",
      "alt": "random"
    },
    {
      "url": "https://fileinfo.com/svg/search-white.svg",
      "alt": "search"
    },
    {
      "url": "https://fileinfo.com/svg/menu.svg",
      "alt": "open menu"
    },
    {
      "url": "https://fileinfo.com/svg/close.svg",
      "alt": "close menu"
    },
    {
      "url": "https://fileinfo.com/svg/settings.svg",
      "alt": "settings"
    }
  ]
}